miniature_lighting_desk/__init__.py
miniature_lighting_desk/async_hal.py
miniature_lighting_desk/cli.py
miniature_lighting_desk/local_gui.py
miniature_lighting_desk/server.py
miniature_lighting_desk-0.6.0.dist-info/LICENSE
miniature_lighting_desk-0.6.0.dist-info/METADATA
miniature_lighting_desk-0.6.0.dist-info/WHEEL
miniature_lighting_desk-0.6.0.dist-info/entry_points.txt
miniature_lighting_desk-0.6.0.dist-info/RECORD
