Metadata-Version: 2.1
Name: miniature-lighting-desk
Version: 0.6.0
Summary: Desk software for Miniature Lighting Controller
License: MIT
Author: John Maximilian
Author-email: 2e0byo@gmail.com
Requires-Python: >=3.9,<4.0
Classifier: License :: OSI Approved :: MIT License
Classifier: Programming Language :: Python :: 3
Classifier: Programming Language :: Python :: 3.9
Classifier: Programming Language :: Python :: 3.10
Classifier: Programming Language :: Python :: 3.11
Requires-Dist: aioserial (>=1.3.1,<2.0.0)
Requires-Dist: autobahn[serialization] (>=23.6.2,<24.0.0)
Requires-Dist: click (>=8.0.3,<9.0.0)
Requires-Dist: coloredlogs (>=15.0.1,<16.0.0)
Requires-Dist: jsonrpcclient (>=4.0.3,<5.0.0)
Requires-Dist: mkdocstrings (>=0.17.0,<0.18.0)
Requires-Dist: pyserial (>=3.5,<4.0)
Requires-Dist: pyusb (>=1.2.1,<2.0.0)
Requires-Dist: rich (>=13.4.2,<14.0.0)
Requires-Dist: typer (>=0.9.0,<0.10.0)
